src/hdl/spi/SPI_MASTER.v


 /*
    Module  : SPI_MASTER
    Version : 1.1
    Author  : Herzog Cyril
    Date    : 2019

	change:
	- internal filter is removed

	info:
	- this old version has a bad fsm design =>

	ToDo (optional): Change FSM - Encoding to "ONE HOT"
	      Control datapath only by state => (mux_sel = state...)

*/


`ifndef _SPI_MASTER_V_
`define _SPI_MASTER_V_


module SPI_MASTER
#(

	parameter   
		CPHA               = 0,
		CPOL               = 0,
		TRANSFER_FREQUENCY = 1000000,
		DATA_WIDTH         = 16,
		BOARD_FREQUENCY    = 50000000
)

		
(
	input CLK, RESET, ENABLE, SDI,
	input[7:0] LENGTH,				//Lenght in Bytes 
	output SCLK, SDO, SS,
	input[DATA_WIDTH-1:0] DATA_IN,
	output[DATA_WIDTH-1:0] DATA_OUT,
	output reg DONE  
);


// change encoding
localparam [1:0]
	idle     = 2'b00,
	delay    = 2'b01,
	clk_t1   = 2'b10,
	clk_t2   = 2'b11;


		
localparam sc_t   = (BOARD_FREQUENCY / TRANSFER_FREQUENCY);
localparam f_sc_t = sc_t - 1; 
localparam h_sc_t = (sc_t / 2) -1;


	
reg[1:0] state_reg, state_next;
reg[DATA_WIDTH-1:0] rx_reg, tx_reg, rx_next, tx_next;
reg[7:0] c_reg, c_next;	
reg[10:0] n_reg, n_next;
reg ss_reg, ss_next, sc_reg, sc_next;
wire[10:0] full_data; 

assign full_data = LENGTH << 3;


	
	
always@(posedge CLK, negedge RESET)
	if (~RESET) 
		begin
		c_reg   	<= 0;
		n_reg   	<= 0;
		rx_reg  	<= 0;
		tx_reg  	<= 0;
		ss_reg  	<= 1'b1;
		state_reg   <= idle;
		sc_reg      <= CPOL;
		end
	else 
		begin
		state_reg   <= state_next;
		sc_reg  	<= sc_next;
		ss_reg  	<= ss_next;
		c_reg   	<= c_next;
		n_reg   	<= n_next;
		rx_reg  	<= rx_next;
		tx_reg  	<= tx_next;
	end

	
	
always@ *
	begin
	c_next     = c_reg;
	n_next     = n_reg;
	sc_next    = sc_reg;
	ss_next    = ss_reg;
	tx_next    = tx_reg;
	rx_next    = rx_reg;
	state_next = state_reg;
	
	DONE       = 1'b0;    // Tick when Transfer ending

		
	case(state_reg)
		idle: 
		begin
			sc_next = CPOL;
			if (ENABLE)
				begin
				state_next  = delay;
				ss_next     = 1'b0;
				end
			end
		
		//delay for 1 spi clk cycle 
		delay:
		begin
			if (c_reg == f_sc_t)
				begin
				if (n_reg == full_data) //  multiplexer is not only control by state => complex logic 
					begin
					state_next  = idle;
					c_next      = 0;
					n_next      = 0;
					ss_next     = 1'b1;
					DONE        = 1'b1;
					end
				else
					begin
					state_next = clk_t1;
					c_next     = 0;
					tx_next    = DATA_IN;
					end
				end
			else
				begin
				c_next = c_reg + 1;
				end
			end
					
				
		clk_t1:
		begin
			if (c_reg == h_sc_t)
				begin
				state_next  = clk_t2;
				c_next      = 0;
		
				if(~CPHA) // parameter
					begin
					rx_next = {rx_reg[DATA_WIDTH-2:0], SDI};
					end
				end
			else
				begin
				c_next = c_reg + 1;
				
				if(~CPOL) // parameter
					begin
					sc_next = 1'b0;
					end
				else
					begin
					sc_next = 1'b1;
				end
			end
		end
			

		clk_t2:
		begin
			if (n_reg == full_data)
				begin
				state_next  = delay;
				sc_next     = CPOL;
				tx_next     = 0;
				end
			else if (c_reg == h_sc_t)
				begin
				c_next      = 0;
				state_next  = clk_t1;
				n_next      = n_reg + 1;
				tx_next     = {tx_reg[DATA_WIDTH-2:0], 1'b0};
				if(CPHA)
					begin
					rx_next = {rx_reg[DATA_WIDTH-2:0], SDI};
					end
				end
			else
				begin
				c_next = c_reg + 1;
				if(CPOL)
					sc_next = 1'b0;
				else
					sc_next = 1'b1;
				end
			end
			
		endcase
	end
	
	assign SDO      = (~ss_reg) ? tx_reg[DATA_WIDTH-1] : 1'bz; 
	assign SCLK     = sc_reg;
	assign SS       = ss_reg;
	assign DATA_OUT = rx_reg;

endmodule

`endif /* SPI_MASTER */

src/hdl/spi/sim/SPI_MASTER_TB.v

`timescale 10ns / 1ns

// sending / resceiving 2 bytes 

module SPI_MASTER_TB;

reg sim_clk, sim_rst;
reg sim_en, bit1;
reg[7:0] sim_len;
reg[15:0] sim_dtx, sim_drx;
wire[15:0] net_drx;
wire net_sclk, net_sdo, net_ss, net_done, sim_sdi;





initial 
	begin
	sim_clk = 1'b0;
	forever
		#1 sim_clk = ~sim_clk;
	end	



// Dumpfile und Dumpvars für GtkWave
initial begin
    $dumpfile("sim/icarus/spi.vcd");
    $dumpvars(0, SPI_MASTER_TB);
end


initial
	begin
	#0   
		sim_rst = 1'b0;
		sim_en  = 1'b0;
		bit1    = 1'b0;
		sim_dtx = 16'b11000001_00000011;
		sim_drx = 16'b00000101_00001000;
	    sim_len = 2;
		$display("tx_data = %b, sim_rx = %b", sim_dtx, sim_drx);
		
	#5 
		sim_rst = 1'b1;
		sim_en  = 1'b1;
		
	#10
		sim_en  = 1'b1;
		
	#15 
		sim_en = 1'b0;
		repeat(16) @(posedge net_sclk)
			if (bit1 == 1'b1)
				begin
				sim_drx = sim_drx << 1;
				end
			else
				begin
				bit1 = 1'b1; 
				end
		
		
	#300
		$finish;
		
	end	

	
assign sim_sdi = sim_drx[15];
	
SPI_MASTER #(0,0,2000000, 16, 50000000) dut0
(
	.CLK(sim_clk),
	.RESET(sim_rst),
	.ENABLE(sim_en),
	.LENGTH(sim_len),
	.SDI(sim_sdi),
	.SCLK(net_sclk),
	.SS(net_ss),
	.SDO(net_sdo),
	.DATA_IN(sim_dtx),
	.DATA_OUT(net_drx),
	.DONE(net_done)
	
);
	   
endmodule

src/hdl/spi/sim/icarus/spi.vcd
$date
	Mon Oct 28 16:24:10 2024
$end
$version
	Icarus Verilog
$end
$timescale
	1ns
$end
$scope module SPI_MASTER_TB $end
$var wire 1 ! sim_sdi $end
$var wire 1 " net_ss $end
$var wire 1 # net_sdo $end
$var wire 1 $ net_sclk $end
$var wire 16 % net_drx [15:0] $end
$var wire 1 & net_done $end
$var reg 1 ' bit1 $end
$var reg 1 ( sim_clk $end
$var reg 16 ) sim_drx [15:0] $end
$var reg 16 * sim_dtx [15:0] $end
$var reg 1 + sim_en $end
$var reg 8 , sim_len [7:0] $end
$var reg 1 - sim_rst $end
$scope module dut0 $end
$var wire 1 ( CLK $end
$var wire 16 . DATA_IN [15:0] $end
$var wire 16 / DATA_OUT [15:0] $end
$var wire 1 + ENABLE $end
$var wire 8 0 LENGTH [7:0] $end
$var wire 1 - RESET $end
$var wire 1 $ SCLK $end
$var wire 1 ! SDI $end
$var wire 1 " SS $end
$var wire 11 1 full_data [10:0] $end
$var wire 1 # SDO $end
$var parameter 32 2 BOARD_FREQUENCY $end
$var parameter 32 3 CPHA $end
$var parameter 32 4 CPOL $end
$var parameter 32 5 DATA_WIDTH $end
$var parameter 32 6 TRANSFER_FREQUENCY $end
$var parameter 2 7 clk_t1 $end
$var parameter 2 8 clk_t2 $end
$var parameter 2 9 delay $end
$var parameter 33 : f_sc_t $end
$var parameter 33 ; h_sc_t $end
$var parameter 2 < idle $end
$var parameter 32 = sc_t $end
$var reg 1 & DONE $end
$var reg 8 > c_next [7:0] $end
$var reg 8 ? c_reg [7:0] $end
$var reg 11 @ n_next [10:0] $end
$var reg 11 A n_reg [10:0] $end
$var reg 16 B rx_next [15:0] $end
$var reg 16 C rx_reg [15:0] $end
$var reg 1 D sc_next $end
$var reg 1 E sc_reg $end
$var reg 1 F ss_next $end
$var reg 1 G ss_reg $end
$var reg 2 H state_next [1:0] $end
$var reg 2 I state_reg [1:0] $end
$var reg 16 J tx_next [15:0] $end
$var reg 16 K tx_reg [15:0] $end
$upscope $end
$upscope $end
$enddefinitions $end
$comment Show the parameter values. $end
$dumpall
b11001 =
b0 <
b1011 ;
b11000 :
b1 9
b11 8
b10 7
b111101000010010000000 6
b10000 5
b0 4
b0 3
b10111110101111000010000000 2
$end
#0
$dumpvars
b0 K
b0 J
b0 I
b0 H
1G
1F
0E
0D
b0 C
b0 B
b0 A
b0 @
b0 ?
b0 >
b10000 1
b10 0
b0 /
b1100000100000011 .
0-
b10 ,
0+
b1100000100000011 *
b10100001000 )
0(
0'
0&
b0 %
0$
z#
1"
0!
$end
#10
1(
#20
0(
#30
1(
#40
0(
#50
0#
b1 >
0"
0G
b1 I
0F
b1 H
1(
1+
1-
#60
0(
#70
b10 >
b1 ?
1(
#80
0(
#90
b11 >
b10 ?
1(
#100
0(
#110
b100 >
b11 ?
1(
#120
0(
#130
b101 >
b100 ?
1(
#140
0(
#150
b110 >
b101 ?
1(
#160
0(
#170
b111 >
b110 ?
1(
#180
0(
#190
b1000 >
b111 ?
1(
#200
0(
#210
b1001 >
b1000 ?
1(
#220
0(
#230
b1010 >
b1001 ?
1(
#240
0(
#250
b1011 >
b1010 ?
1(
#260
0(
#270
b1100 >
b1011 ?
1(
#280
0(
#290
b1101 >
b1100 ?
1(
#300
b1101 >
0(
0+
#310
b1110 >
b1101 ?
1(
#320
0(
#330
b1111 >
b1110 ?
1(
#340
0(
#350
b10000 >
b1111 ?
1(
#360
0(
#370
b10001 >
b10000 ?
1(
#380
0(
#390
b10010 >
b10001 ?
1(
#400
0(
#410
b10011 >
b10010 ?
1(
#420
0(
#430
b10100 >
b10011 ?
1(
#440
0(
#450
b10101 >
b10100 ?
1(
#460
0(
#470
b10110 >
b10101 ?
1(
#480
0(
#490
b10111 >
b10110 ?
1(
#500
0(
#510
b11000 >
b10111 ?
1(
#520
0(
#530
b1100000100000011 J
b0 >
b10 H
b11000 ?
1(
#540
0(
#550
1#
b1 >
b1100000100000011 K
b0 ?
b10 I
1(
#560
0(
#570
b10 >
b1 ?
1(
#580
0(
#590
b11 >
b10 ?
1(
#600
0(
#610
b100 >
b11 ?
1(
#620
0(
#630
b101 >
b100 ?
1(
#640
0(
#650
b110 >
b101 ?
1(
#660
0(
#670
b111 >
b110 ?
1(
#680
0(
#690
b1000 >
b111 ?
1(
#700
0(
#710
b1001 >
b1000 ?
1(
#720
0(
#730
b1010 >
b1001 ?
1(
#740
0(
#750
b1011 >
b1010 ?
1(
#760
0(
#770
b0 >
b11 H
b1011 ?
1(
#780
0(
#790
1D
b1 >
b0 ?
b11 I
1(
#800
0(
#810
b10 >
1'
b1 ?
1$
1E
1(
#820
0(
#830
b11 >
b10 ?
1(
#840
0(
#850
b100 >
b11 ?
1(
#860
0(
#870
b101 >
b100 ?
1(
#880
0(
#890
b110 >
b101 ?
1(
#900
0(
#910
b111 >
b110 ?
1(
#920
0(
#930
b1000 >
b111 ?
1(
#940
0(
#950
b1001 >
b1000 ?
1(
#960
0(
#970
b1010 >
b1001 ?
1(
#980
0(
#990
b1011 >
b1010 ?
1(
#1000
0(
#1010
b1000001000000110 J
b1 @
b10 H
b0 >
b1011 ?
1(
#1020
0(
#1030
0D
b1 >
b1000001000000110 K
b1 A
b0 ?
b10 I
1(
#1040
0(
#1050
b10 >
b1 ?
0$
0E
1(
#1060
0(
#1070
b11 >
b10 ?
1(
#1080
0(
#1090
b100 >
b11 ?
1(
#1100
0(
#1110
b101 >
b100 ?
1(
#1120
0(
#1130
b110 >
b101 ?
1(
#1140
0(
#1150
b111 >
b110 ?
1(
#1160
0(
#1170
b1000 >
b111 ?
1(
#1180
0(
#1190
b1001 >
b1000 ?
1(
#1200
0(
#1210
b1010 >
b1001 ?
1(
#1220
0(
#1230
b1011 >
b1010 ?
1(
#1240
0(
#1250
b0 >
b11 H
b1011 ?
1(
#1260
0(
#1270
1D
b1 >
b0 ?
b11 I
1(
#1280
0(
#1290
b10 >
b101000010000 )
b1 ?
1$
1E
1(
#1300
0(
#1310
b11 >
b10 ?
1(
#1320
0(
#1330
b100 >
b11 ?
1(
#1340
0(
#1350
b101 >
b100 ?
1(
#1360
0(
#1370
b110 >
b101 ?
1(
#1380
0(
#1390
b111 >
b110 ?
1(
#1400
0(
#1410
b1000 >
b111 ?
1(
#1420
0(
#1430
b1001 >
b1000 ?
1(
#1440
0(
#1450
b1010 >
b1001 ?
1(
#1460
0(
#1470
b1011 >
b1010 ?
1(
#1480
0(
#1490
b10000001100 J
b10 @
b10 H
b0 >
b1011 ?
1(
#1500
0(
#1510
0#
0D
b1 >
b10000001100 K
b10 A
b0 ?
b10 I
1(
#1520
0(
#1530
b10 >
b1 ?
0$
0E
1(
#1540
0(
#1550
b11 >
b10 ?
1(
#1560
0(
#1570
b100 >
b11 ?
1(
#1580
0(
#1590
b101 >
b100 ?
1(
#1600
0(
#1610
b110 >
b101 ?
1(
#1620
0(
#1630
b111 >
b110 ?
1(
#1640
0(
#1650
b1000 >
b111 ?
1(
#1660
0(
#1670
b1001 >
b1000 ?
1(
#1680
0(
#1690
b1010 >
b1001 ?
1(
#1700
0(
#1710
b1011 >
b1010 ?
1(
#1720
0(
#1730
b0 >
b11 H
b1011 ?
1(
#1740
0(
#1750
1D
b1 >
b0 ?
b11 I
1(
#1760
0(
#1770
b10 >
b1010000100000 )
b1 ?
1$
1E
1(
#1780
0(
#1790
b11 >
b10 ?
1(
#1800
0(
#1810
b100 >
b11 ?
1(
#1820
0(
#1830
b101 >
b100 ?
1(
#1840
0(
#1850
b110 >
b101 ?
1(
#1860
0(
#1870
b111 >
b110 ?
1(
#1880
0(
#1890
b1000 >
b111 ?
1(
#1900
0(
#1910
b1001 >
b1000 ?
1(
#1920
0(
#1930
b1010 >
b1001 ?
1(
#1940
0(
#1950
b1011 >
b1010 ?
1(
#1960
0(
#1970
b100000011000 J
b11 @
b10 H
b0 >
b1011 ?
1(
#1980
0(
#1990
0D
b1 >
b100000011000 K
b11 A
b0 ?
b10 I
1(
#2000
0(
#2010
b10 >
b1 ?
0$
0E
1(
#2020
0(
#2030
b11 >
b10 ?
1(
#2040
0(
#2050
b100 >
b11 ?
1(
#2060
0(
#2070
b101 >
b100 ?
1(
#2080
0(
#2090
b110 >
b101 ?
1(
#2100
0(
#2110
b111 >
b110 ?
1(
#2120
0(
#2130
b1000 >
b111 ?
1(
#2140
0(
#2150
b1001 >
b1000 ?
1(
#2160
0(
#2170
b1010 >
b1001 ?
1(
#2180
0(
#2190
b1011 >
b1010 ?
1(
#2200
0(
#2210
b0 >
b11 H
b1011 ?
1(
#2220
0(
#2230
1D
b1 >
b0 ?
b11 I
1(
#2240
0(
#2250
b10 >
b10100001000000 )
b1 ?
1$
1E
1(
#2260
0(
#2270
b11 >
b10 ?
1(
#2280
0(
#2290
b100 >
b11 ?
1(
#2300
0(
#2310
b101 >
b100 ?
1(
#2320
0(
#2330
b110 >
b101 ?
1(
#2340
0(
#2350
b111 >
b110 ?
1(
#2360
0(
#2370
b1000 >
b111 ?
1(
#2380
0(
#2390
b1001 >
b1000 ?
1(
#2400
0(
#2410
b1010 >
b1001 ?
1(
#2420
0(
#2430
b1011 >
b1010 ?
1(
#2440
0(
#2450
b1000000110000 J
b100 @
b10 H
b0 >
b1011 ?
1(
#2460
0(
#2470
0D
b1 >
b1000000110000 K
b100 A
b0 ?
b10 I
1(
#2480
0(
#2490
b10 >
b1 ?
0$
0E
1(
#2500
0(
#2510
b11 >
b10 ?
1(
#2520
0(
#2530
b100 >
b11 ?
1(
#2540
0(
#2550
b101 >
b100 ?
1(
#2560
0(
#2570
b110 >
b101 ?
1(
#2580
0(
#2590
b111 >
b110 ?
1(
#2600
0(
#2610
b1000 >
b111 ?
1(
#2620
0(
#2630
b1001 >
b1000 ?
1(
#2640
0(
#2650
b1010 >
b1001 ?
1(
#2660
0(
#2670
b1011 >
b1010 ?
1(
#2680
0(
#2690
b0 >
b11 H
b1011 ?
1(
#2700
0(
#2710
1D
b1 >
b0 ?
b11 I
1(
#2720
0(
#2730
b10 >
b101000010000000 )
b1 ?
1$
1E
1(
#2740
0(
#2750
b11 >
b10 ?
1(
#2760
0(
#2770
b100 >
b11 ?
1(
#2780
0(
#2790
b101 >
b100 ?
1(
#2800
0(
#2810
b110 >
b101 ?
1(
#2820
0(
#2830
b111 >
b110 ?
1(
#2840
0(
#2850
b1000 >
b111 ?
1(
#2860
0(
#2870
b1001 >
b1000 ?
1(
#2880
0(
#2890
b1010 >
b1001 ?
1(
#2900
0(
#2910
b1011 >
b1010 ?
1(
#2920
0(
#2930
b10000001100000 J
b101 @
b10 H
b0 >
b1011 ?
1(
#2940
0(
#2950
0D
b1 >
b10000001100000 K
b101 A
b0 ?
b10 I
1(
#2960
0(
#2970
b10 >
b1 ?
0$
0E
1(
#2980
0(
#2990
b11 >
b10 ?
1(
#3000
0(
#3010
b100 >
b11 ?
1(
#3020
0(
#3030
b101 >
b100 ?
1(
#3040
0(
#3050
b110 >
b101 ?
1(
#3060
0(
#3070
b111 >
b110 ?
1(
#3080
0(
#3090
b1000 >
b111 ?
1(
#3100
0(
#3110
b1001 >
b1000 ?
1(
#3120
0(
#3130
b1010 >
b1001 ?
1(
#3140
0(
#3150
b1011 >
b1010 ?
1(
#3160
0(
#3170
b0 >
b11 H
b1011 ?
1(
#3180
0(
#3190
1D
b1 >
b0 ?
b11 I
1(
#3200
0(
#3210
1!
b10 >
b1010000100000000 )
b1 ?
1$
1E
1(
#3220
0(
#3230
b11 >
b10 ?
1(
#3240
0(
#3250
b100 >
b11 ?
1(
#3260
0(
#3270
b101 >
b100 ?
1(
#3280
0(
#3290
b110 >
b101 ?
1(
#3300
0(
#3310
b111 >
b110 ?
1(
#3320
0(
#3330
b1000 >
b111 ?
1(
#3340
0(
#3350
b1001 >
b1000 ?
1(
#3360
0(
#3370
b1010 >
b1001 ?
1(
#3380
0(
#3390
b1011 >
b1010 ?
1(
#3400
0(
#3410
b100000011000000 J
b110 @
b10 H
b0 >
b1011 ?
1(
#3420
0(
#3430
0D
b1 >
b100000011000000 K
b110 A
b0 ?
b10 I
1(
#3440
0(
#3450
b10 >
b1 ?
0$
0E
1(
#3460
0(
#3470
b11 >
b10 ?
1(
#3480
0(
#3490
b100 >
b11 ?
1(
#3500
0(
#3510
b101 >
b100 ?
1(
#3520
0(
#3530
b110 >
b101 ?
1(
#3540
0(
#3550
b111 >
b110 ?
1(
#3560
0(
#3570
b1000 >
b111 ?
1(
#3580
0(
#3590
b1001 >
b1000 ?
1(
#3600
0(
#3610
b1010 >
b1001 ?
1(
#3620
0(
#3630
b1011 >
b1010 ?
1(
#3640
0(
#3650
b1 B
b0 >
b11 H
b1011 ?
1(
#3660
0(
#3670
1D
b1 >
b1 %
b1 /
b1 C
b0 ?
b11 I
1(
#3680
0(
#3690
0!
b10 >
b100001000000000 )
b1 ?
1$
1E
1(
#3700
0(
#3710
b11 >
b10 ?
1(
#3720
0(
#3730
b100 >
b11 ?
1(
#3740
0(
#3750
b101 >
b100 ?
1(
#3760
0(
#3770
b110 >
b101 ?
1(
#3780
0(
#3790
b111 >
b110 ?
1(
#3800
0(
#3810
b1000 >
b111 ?
1(
#3820
0(
#3830
b1001 >
b1000 ?
1(
#3840
0(
#3850
b1010 >
b1001 ?
1(
#3860
0(
#3870
b1011 >
b1010 ?
1(
#3880
0(
#3890
b1000000110000000 J
b111 @
b10 H
b0 >
b1011 ?
1(
#3900
0(
#3910
1#
0D
b1 >
b1000000110000000 K
b111 A
b0 ?
b10 I
1(
#3920
0(
#3930
b10 >
b1 ?
0$
0E
1(
#3940
0(
#3950
b11 >
b10 ?
1(
#3960
0(
#3970
b100 >
b11 ?
1(
#3980
0(
#3990
b101 >
b100 ?
1(
#4000
0(
#4010
b110 >
b101 ?
1(
#4020
0(
#4030
b111 >
b110 ?
1(
#4040
0(
#4050
b1000 >
b111 ?
1(
#4060
0(
#4070
b1001 >
b1000 ?
1(
#4080
0(
#4090
b1010 >
b1001 ?
1(
#4100
0(
#4110
b1011 >
b1010 ?
1(
#4120
0(
#4130
b10 B
b0 >
b11 H
b1011 ?
1(
#4140
0(
#4150
1D
b1 >
b10 %
b10 /
b10 C
b0 ?
b11 I
1(
#4160
0(
#4170
1!
b10 >
b1000010000000000 )
b1 ?
1$
1E
1(
#4180
0(
#4190
b11 >
b10 ?
1(
#4200
0(
#4210
b100 >
b11 ?
1(
#4220
0(
#4230
b101 >
b100 ?
1(
#4240
0(
#4250
b110 >
b101 ?
1(
#4260
0(
#4270
b111 >
b110 ?
1(
#4280
0(
#4290
b1000 >
b111 ?
1(
#4300
0(
#4310
b1001 >
b1000 ?
1(
#4320
0(
#4330
b1010 >
b1001 ?
1(
#4340
0(
#4350
b1011 >
b1010 ?
1(
#4360
0(
#4370
b1100000000 J
b1000 @
b10 H
b0 >
b1011 ?
1(
#4380
0(
#4390
0#
0D
b1 >
b1100000000 K
b1000 A
b0 ?
b10 I
1(
#4400
0(
#4410
b10 >
b1 ?
0$
0E
1(
#4420
0(
#4430
b11 >
b10 ?
1(
#4440
0(
#4450
b100 >
b11 ?
1(
#4460
0(
#4470
b101 >
b100 ?
1(
#4480
0(
#4490
b110 >
b101 ?
1(
#4500
0(
#4510
b111 >
b110 ?
1(
#4520
0(
#4530
b1000 >
b111 ?
1(
#4540
0(
#4550
b1001 >
b1000 ?
1(
#4560
0(
#4570
b1010 >
b1001 ?
1(
#4580
0(
#4590
b1011 >
b1010 ?
1(
#4600
0(
#4610
b101 B
b0 >
b11 H
b1011 ?
1(
#4620
0(
#4630
1D
b1 >
b101 %
b101 /
b101 C
b0 ?
b11 I
1(
#4640
0(
#4650
0!
b10 >
b100000000000 )
b1 ?
1$
1E
1(
#4660
0(
#4670
b11 >
b10 ?
1(
#4680
0(
#4690
b100 >
b11 ?
1(
#4700
0(
#4710
b101 >
b100 ?
1(
#4720
0(
#4730
b110 >
b101 ?
1(
#4740
0(
#4750
b111 >
b110 ?
1(
#4760
0(
#4770
b1000 >
b111 ?
1(
#4780
0(
#4790
b1001 >
b1000 ?
1(
#4800
0(
#4810
b1010 >
b1001 ?
1(
#4820
0(
#4830
b1011 >
b1010 ?
1(
#4840
0(
#4850
b11000000000 J
b1001 @
b10 H
b0 >
b1011 ?
1(
#4860
0(
#4870
0D
b1 >
b11000000000 K
b1001 A
b0 ?
b10 I
1(
#4880
0(
#4890
b10 >
b1 ?
0$
0E
1(
#4900
0(
#4910
b11 >
b10 ?
1(
#4920
0(
#4930
b100 >
b11 ?
1(
#4940
0(
#4950
b101 >
b100 ?
1(
#4960
0(
#4970
b110 >
b101 ?
1(
#4980
0(
#4990
b111 >
b110 ?
1(
#5000
0(
#5010
b1000 >
b111 ?
1(
#5020
0(
#5030
b1001 >
b1000 ?
1(
#5040
0(
#5050
b1010 >
b1001 ?
1(
#5060
0(
#5070
b1011 >
b1010 ?
1(
#5080
0(
#5090
b1010 B
b0 >
b11 H
b1011 ?
1(
#5100
0(
#5110
1D
b1 >
b1010 %
b1010 /
b1010 C
b0 ?
b11 I
1(
#5120
0(
#5130
b10 >
b1000000000000 )
b1 ?
1$
1E
1(
#5140
0(
#5150
b11 >
b10 ?
1(
#5160
0(
#5170
b100 >
b11 ?
1(
#5180
0(
#5190
b101 >
b100 ?
1(
#5200
0(
#5210
b110 >
b101 ?
1(
#5220
0(
#5230
b111 >
b110 ?
1(
#5240
0(
#5250
b1000 >
b111 ?
1(
#5260
0(
#5270
b1001 >
b1000 ?
1(
#5280
0(
#5290
b1010 >
b1001 ?
1(
#5300
0(
#5310
b1011 >
b1010 ?
1(
#5320
0(
#5330
b110000000000 J
b1010 @
b10 H
b0 >
b1011 ?
1(
#5340
0(
#5350
0D
b1 >
b110000000000 K
b1010 A
b0 ?
b10 I
1(
#5360
0(
#5370
b10 >
b1 ?
0$
0E
1(
#5380
0(
#5390
b11 >
b10 ?
1(
#5400
0(
#5410
b100 >
b11 ?
1(
#5420
0(
#5430
b101 >
b100 ?
1(
#5440
0(
#5450
b110 >
b101 ?
1(
#5460
0(
#5470
b111 >
b110 ?
1(
#5480
0(
#5490
b1000 >
b111 ?
1(
#5500
0(
#5510
b1001 >
b1000 ?
1(
#5520
0(
#5530
b1010 >
b1001 ?
1(
#5540
0(
#5550
b1011 >
b1010 ?
1(
#5560
0(
#5570
b10100 B
b0 >
b11 H
b1011 ?
1(
#5580
0(
#5590
1D
b1 >
b10100 %
b10100 /
b10100 C
b0 ?
b11 I
1(
#5600
0(
#5610
b10 >
b10000000000000 )
b1 ?
1$
1E
1(
#5620
0(
#5630
b11 >
b10 ?
1(
#5640
0(
#5650
b100 >
b11 ?
1(
#5660
0(
#5670
b101 >
b100 ?
1(
#5680
0(
#5690
b110 >
b101 ?
1(
#5700
0(
#5710
b111 >
b110 ?
1(
#5720
0(
#5730
b1000 >
b111 ?
1(
#5740
0(
#5750
b1001 >
b1000 ?
1(
#5760
0(
#5770
b1010 >
b1001 ?
1(
#5780
0(
#5790
b1011 >
b1010 ?
1(
#5800
0(
#5810
b1100000000000 J
b1011 @
b10 H
b0 >
b1011 ?
1(
#5820
0(
#5830
0D
b1 >
b1100000000000 K
b1011 A
b0 ?
b10 I
1(
#5840
0(
#5850
b10 >
b1 ?
0$
0E
1(
#5860
0(
#5870
b11 >
b10 ?
1(
#5880
0(
#5890
b100 >
b11 ?
1(
#5900
0(
#5910
b101 >
b100 ?
1(
#5920
0(
#5930
b110 >
b101 ?
1(
#5940
0(
#5950
b111 >
b110 ?
1(
#5960
0(
#5970
b1000 >
b111 ?
1(
#5980
0(
#5990
b1001 >
b1000 ?
1(
#6000
0(
#6010
b1010 >
b1001 ?
1(
#6020
0(
#6030
b1011 >
b1010 ?
1(
#6040
0(
#6050
b101000 B
b0 >
b11 H
b1011 ?
1(
#6060
0(
#6070
1D
b1 >
b101000 %
b101000 /
b101000 C
b0 ?
b11 I
1(
#6080
0(
#6090
b10 >
b100000000000000 )
b1 ?
1$
1E
1(
#6100
0(
#6110
b11 >
b10 ?
1(
#6120
0(
#6130
b100 >
b11 ?
1(
#6140
0(
#6150
b101 >
b100 ?
1(
#6160
0(
#6170
b110 >
b101 ?
1(
#6180
0(
#6190
b111 >
b110 ?
1(
#6200
0(
#6210
b1000 >
b111 ?
1(
#6220
0(
#6230
b1001 >
b1000 ?
1(
#6240
0(
#6250
b1010 >
b1001 ?
1(
#6260
0(
#6270
b1011 >
b1010 ?
1(
#6280
0(
#6290
b11000000000000 J
b1100 @
b10 H
b0 >
b1011 ?
1(
#6300
0(
#6310
0D
b1 >
b11000000000000 K
b1100 A
b0 ?
b10 I
1(
#6320
0(
#6330
b10 >
b1 ?
0$
0E
1(
#6340
0(
#6350
b11 >
b10 ?
1(
#6360
0(
#6370
b100 >
b11 ?
1(
#6380
0(
#6390
b101 >
b100 ?
1(
#6400
0(
#6410
b110 >
b101 ?
1(
#6420
0(
#6430
b111 >
b110 ?
1(
#6440
0(
#6450
b1000 >
b111 ?
1(
#6460
0(
#6470
b1001 >
b1000 ?
1(
#6480
0(
#6490
b1010 >
b1001 ?
1(
#6500
0(
#6510
b1011 >
b1010 ?
1(
#6520
0(
#6530
b1010000 B
b0 >
b11 H
b1011 ?
1(
#6540
0(
#6550
1D
b1 >
b1010000 %
b1010000 /
b1010000 C
b0 ?
b11 I
1(
#6560
0(
#6570
1!
b10 >
b1000000000000000 )
b1 ?
1$
1E
1(
#6580
0(
#6590
b11 >
b10 ?
1(
#6600
0(
#6610
b100 >
b11 ?
1(
#6620
0(
#6630
b101 >
b100 ?
1(
#6640
0(
#6650
b110 >
b101 ?
1(
#6660
0(
#6670
b111 >
b110 ?
1(
#6680
0(
#6690
b1000 >
b111 ?
1(
#6700
0(
#6710
b1001 >
b1000 ?
1(
#6720
0(
#6730
b1010 >
b1001 ?
1(
#6740
0(
#6750
b1011 >
b1010 ?
1(
#6760
0(
#6770
b110000000000000 J
b1101 @
b10 H
b0 >
b1011 ?
1(
#6780
0(
#6790
0D
b1 >
b110000000000000 K
b1101 A
b0 ?
b10 I
1(
#6800
0(
#6810
b10 >
b1 ?
0$
0E
1(
#6820
0(
#6830
b11 >
b10 ?
1(
#6840
0(
#6850
b100 >
b11 ?
1(
#6860
0(
#6870
b101 >
b100 ?
1(
#6880
0(
#6890
b110 >
b101 ?
1(
#6900
0(
#6910
b111 >
b110 ?
1(
#6920
0(
#6930
b1000 >
b111 ?
1(
#6940
0(
#6950
b1001 >
b1000 ?
1(
#6960
0(
#6970
b1010 >
b1001 ?
1(
#6980
0(
#6990
b1011 >
b1010 ?
1(
#7000
0(
#7010
b10100001 B
b0 >
b11 H
b1011 ?
1(
#7020
0(
#7030
1D
b1 >
b10100001 %
b10100001 /
b10100001 C
b0 ?
b11 I
1(
#7040
0(
#7050
0!
b10 >
b0 )
b1 ?
1$
1E
1(
#7060
0(
#7070
b11 >
b10 ?
1(
#7080
0(
#7090
b100 >
b11 ?
1(
#7100
0(
#7110
b101 >
b100 ?
1(
#7120
0(
#7130
b110 >
b101 ?
1(
#7140
0(
#7150
b111 >
b110 ?
1(
#7160
0(
#7170
b1000 >
b111 ?
1(
#7180
0(
#7190
b1001 >
b1000 ?
1(
#7200
0(
#7210
b1010 >
b1001 ?
1(
#7220
0(
#7230
b1011 >
b1010 ?
1(
#7240
0(
#7250
b1100000000000000 J
b1110 @
b10 H
b0 >
b1011 ?
1(
#7260
0(
#7270
1#
0D
b1 >
b1100000000000000 K
b1110 A
b0 ?
b10 I
1(
#7280
0(
#7290
b10 >
b1 ?
0$
0E
1(
#7300
0(
#7310
b11 >
b10 ?
1(
#7320
0(
#7330
b100 >
b11 ?
1(
#7340
0(
#7350
b101 >
b100 ?
1(
#7360
0(
#7370
b110 >
b101 ?
1(
#7380
0(
#7390
b111 >
b110 ?
1(
#7400
0(
#7410
b1000 >
b111 ?
1(
#7420
0(
#7430
b1001 >
b1000 ?
1(
#7440
0(
#7450
b1010 >
b1001 ?
1(
#7460
0(
#7470
b1011 >
b1010 ?
1(
#7480
0(
